kpclibpy/__init__.py
kpclibpy/__main__.py
kpclibpy/nubia_context.py
kpclibpy/nubia_plugin.py
kpclibpy/nubia_statusbar.py
kpclibpy/unit_test.ipynb
kpclibpy/commands/__init__.py
kpclibpy/commands/database_cmds.py
kpclibpy/commands/keepass.py
kpclibpy/commands/entry/__init__.py
kpclibpy/commands/entry/entry_commands.py
kpclibpy/commands/group/__init__.py
kpclibpy/commands/group/group_commands.py
kpclibpy/kpclib/__init__.py
kpclibpy/kpclib/kpclib.py
kpclibpy/kpclib/lib/KPCLib.dll
kpclibpy/kpclib/lib/Microsoft.AspNetCore.WebUtilities.dll
kpclibpy/kpclib/lib/Microsoft.Extensions.Primitives.dll
kpclibpy/kpclib/lib/PassXYZ.dll
kpclibpy/kpclib/lib/PassXYZLib.dll
kpclibpy/kpclib/lib/PureOtp.dll
kpclibpy/kpclib/lib/SkiaSharp.dll
kpclibpy/tests/__init__.py
kpclibpy/tests/conftest.py
kpclibpy/tests/db_test.py
kpclibpy/tests/pwentry_test.ipynb
kpclibpy-1.1.8.dist-info/LICENSE
kpclibpy-1.1.8.dist-info/METADATA
kpclibpy-1.1.8.dist-info/WHEEL
kpclibpy-1.1.8.dist-info/entry_points.txt
kpclibpy-1.1.8.dist-info/top_level.txt
kpclibpy-1.1.8.dist-info/RECORD
