Metadata-Version: 2.1
Name: kpclibpy
Version: 1.1.8
Summary: KeePass command line application
Home-page: https://github.com/passxyz/KPCLibPy
Author: Roger Ye
Author-email: shugaoye@yahoo.com
License: MIT
Platform: UNKNOWN
Classifier: Development Status :: 5 - Production/Stable
Classifier: Intended Audience :: Developers
Classifier: License :: OSI Approved :: MIT License
Classifier: Programming Language :: C#
Classifier: Programming Language :: Python :: 3
Classifier: Programming Language :: Python :: 3.6
Classifier: Programming Language :: Python :: 3.7
Classifier: Programming Language :: Python :: 3.8
Classifier: Programming Language :: Python :: 3.9
Classifier: Operating System :: Microsoft :: Windows
Classifier: Operating System :: POSIX :: Linux
Classifier: Operating System :: MacOS :: MacOS X
Requires-Python: >=3.6
Requires-Dist: pycparser (==2.20)
Requires-Dist: consolemd (>=0.5.1)
Requires-Dist: importlib-metadata (>=3.6)
Requires-Dist: pythonnet (==2.5.2)
Requires-Dist: python-nubia (==0.2b5)
